eywa/__init__.py
eywa/entities/__init__.py
eywa/entities/entities.py
eywa/graph/__init__.py
eywa/graph/graph.py
eywa/graph/namespace.py
eywa/graph/node.py
eywa/graph/nodes.py
eywa/graph/signal.py
eywa/lang/__init__.py
eywa/lang/en/__init__.py
eywa/lang/en/database.py
eywa/lang/en/download_embeddings.py
eywa/lang/en/embedding_utils.py
eywa/lang/en/filenames.py
eywa/lang/en/indexer.py
eywa/lang/en/model.py
eywa/lang/en/stop_words.txt
eywa/lang/en/extractors/__init__.py
eywa/lang/en/extractors/date_time_extractor.py
eywa/lang/en/extractors/entity.py
eywa/lang/en/extractors/extractor.py
eywa/lang/en/extractors/number_extractor.py
eywa/lang/en/extractors/regex_extractors.py
eywa/learn/__init__.py
eywa/learn/evolutionary_strategies.py
eywa/learn/learner.py
eywa/logic/__init__.py
eywa/logic/memory.py
eywa/math/__init__.py
eywa/math/math.py
eywa/math/numba_backend.py
eywa/math/numpy_backend.py
eywa/nlu/__init__.py
eywa/nlu/classifier.py
eywa/nlu/comparator.py
eywa/nlu/entity_extractor.py
eywa/nlu/pattern.py
eywa/nlu/template.py
eywa/utils/__init__.py
eywa/utils/environment.py
eywa/utils/progressbar.py
tests/__init__.py
tests/test_backends.py
tests/test_classifier.py
tests/test_comparator.py
tests/test_entity_extractor.py
tests/test_pattern.py
eywa-0.0.4.dist-info/LICENSE
eywa-0.0.4.dist-info/METADATA
eywa-0.0.4.dist-info/WHEEL
eywa-0.0.4.dist-info/top_level.txt
eywa-0.0.4.dist-info/RECORD
